Metadata-Version: 2.1
Name: nbdbsession
Version: 0.2.7
Summary: Config mgt to connect to databases from jupyter notebooks.
Home-page: https://github.com/davidkuda/jupyter_database_io
Author: David Kuda
License: MIT
License-File: LICENSE
